Workbook

Sheet Inputs
A1: Parameter | B1: Value | C1: Unit
A2: Ore throughput (tpd) | B2: 3800 | C2: t/day
A3: Days per year | B3: 365 | C3: days
A4: Grade | B4: 7.5 | C4: g/t
A5: Recovery | B5: 0.96 | C5: fraction
A6: Mine Life | B6: 10 | C6: years
A8: Gold price | B8: 4500 | C8: USD/oz
A10: FX rate (USD/CAD) | B10: 0.75 | C10: USD/CAD
A12: Mining cost | B12: 110 | C12: CAD/t ore
A13: Processing Cost | B13: 55 | C13: CAD/t ore
A14: G&A | B14: 25 | C14: CAD/t ore
A15: Sustaining capital | B15: 80000000 | C15: CAD/year
A16: Closure cost | B16: 150000000 | C16: CAD (lump sum)
... A18: Discount rate | B18: 0.05 | C18: fraction
A20: Grade multiplier | B20: 1
A21: Effective Grade (g/t) | B21: =B4*B20 -> 7.5

Sheet Production
A1: Year | B1: Ore tonnes | C1: Grade (g/t) | D1: Recovery | E1: Gold ounces
A2: 1 | B2: =Inputs!$B$2 * Inputs!$B$3 -> 1387000 | C2: =Inputs!$B$21 -> 7.5 | D2: =Inputs!$B$5 -> 0.96 | E2: =B2 * C2 * D2 / 31.1035 -> 321069.98
A3: 2 | B3: =Inputs!$B$2 * Inputs!$B$3 -> 1387000 | C3: =Inputs!$B$21 -> 7.5 | D3: =Inputs!$B$5 -> 0.96 | E3: =B3 * C3 * D3 / 31.1035 -> 321069.98
A4: 3 | B4: =Inputs!$B$2 * Inputs!$B$3 -> 1387000 | C4: =Inputs!$B$21 -> 7.5 | D4: =Inputs!$B$5 -> 0.96 | E4: =B4 * C4 * D4 / 31.1035 -> 321069.98
A5: 4 | B5: =Inputs!$B$2 * Inputs!$B$3 -> 1387000 | C5: =Inputs!$B$21 -> 7.5 | D5: =Inputs!$B$5 -> 0.96 | E5: =B5 * C5 * D5 / 31.1035 -> 321069.98
A6: 5 | B6: =Inputs!$B$2 * Inputs!$B$3 -> 1387000 | C6: =Inputs!$B$21 -> 7.5 | D6: =Inputs!$B$5 -> 0.96 | E6: =B6 * C6 * D6 / 31.1035 -> 321069.98
A7: 6 | B7: =Inputs!$B$2 * Inputs!$B$3 -> 1387000 | C7: =Inputs!$B$21 -> 7.5 | D7: =Inputs!$B$5 -> 0.96 | E7: =B7 * C7 * D7 / 31.1035 -> 321069.98
A8: 7 | B8: =Inputs!$B$2 * Inputs!$B$3 -> 1387000 | C8: =Inputs!$B$21 -> 7.5 | D8: =Inputs!$B$5 -> 0.96 | E8: =B8 * C8 * D8 / 31.1035 -> 321069.98
A9: 8 | B9: =Inputs!$B$2 * Inputs!$B$3 -> 1387000 | C9: =Inputs!$B$21 -> 7.5 | D9: =Inputs!$B$5 -> 0.96 | E9: =B9 * C9 * D9 / 31.1035 -> 321069.98
A10: 9 | B10: =Inputs!$B$2 * Inputs!$B$3 -> 1387000 | C10: =Inputs!$B$21 -> 7.5 | D10: =Inputs!$B$5 -> 0.96 | E10: =B10 * C10 * D10 / 31.1035 -> 321069.98
A11: 10 | B11: =Inputs!$B$2 * Inputs!$B$3 -> 1387000 | C11: =Inputs!$B$21 -> 7.5 | D11: =Inputs!$B$5 -> 0.96 | E11: =B11 * C11 * D11 / 31.1035 -> 321069.98

Sheet Costs_AISC
A1: Year | B1: Ore tonnes | C1: Gold ounces | D1: Mining cost (CAD) | E1: Processing cost (CAD) | F1: G&A (CAD) | G1: Sustaining capital (CAD) | H1: Revenue (CAD) | I1: Royalty (CAD) | J1: Total site cost (CAD) | K1: AISC (CAD/oz)
A2: =Production!A2 -> 1 | B2: =Production!B2 -> 1387000 | C2: =Production!E2 -> 321069.98 | D2: =B2 * Inputs!$B$12 -> 152570000 | E2: =B2 * Inputs!$B$13 -> 76285000 | F2: =B2 * Inputs!$B$14 -> 34675000 | G2: =Inputs!$B$15 -> 80000000 | H2: =C2 * Inputs!$B$8 -> 1.4448149e+09 | I2: =H2 * Inputs!$B$17 -> 28896298 | J2: =D2 + E2 + F2 + G2 + I2 -> 3.724263e+08 | K2: =J2 / C2 -> 1159.9537
A3: =Production!A3 -> 2 | B3: =Production!B3 -> 1387000 | C3: =Production!E3 -> 321069.98 | D3: =B3 * Inputs!$B$12 -> 152570000 | E3: =B3 * Inputs!$B$13 -> 76285000 | F3: =B3 * Inputs!$B$14 -> 34675000 | G3: =Inputs!$B$15 -> 80000000 | H3: =C3 * Inputs!$B$8 -> 1.4448149e+09 | I3: =H3 * Inputs!$B$17 -> 28896298 | J3: =D3 + E3 + F3 + G3 + I3 -> 3.724263e+08 | K3: =J3 / C3 -> 1159.9537
A4: =Production!A4 -> 3 | B4: =Production!B4 -> 1387000 | C4: =Production!E4 -> 321069.98 | D4: =B4 * Inputs!$B$12 -> 152570000 | E4: =B4 * Inputs!$B$13 -> 76285000 | F4: =B4 * Inputs!$B$14 -> 34675000 | G4: =Inputs!$B$15 -> 80000000 | H4: =C4 * Inputs!$B$8 -> 1.4448149e+09 | I4: =H4 * Inputs!$B$17 -> 28896298 | J4: =D4 + E4 + F4 + G4 + I4 -> 3.724263e+08 | K4: =J4 / C4 -> 1159.9537
A5: =Production!A5 -> 4 | B5: =Production!B5 -> 1387000 | C5: =Production!E5 -> 321069.98 | D5: =B5 * Inputs!$B$12 -> 152570000 | E5: =B5 * Inputs!$B$13 -> 76285000 | F5: =B5 * Inputs!$B$14 -> 34675000 | G5: =Inputs!$B$15 -> 80000000 | H5: =C5 * Inputs!$B$8 -> 1.4448149e+09 | I5: =H5 * Inputs!$B$17 -> 28896298 | J5: =D5 + E5 + F5 + G5 + I5 -> 3.724263e+08 | K5: =J5 / C5 -> 1159.9537
A6: =Production!A6 -> 5 | B6: =Production!B6 -> 1387000 | C6: =Production!E6 -> 321069.98 | D6: =B6 * Inputs!$B$12 -> 152570000 | E6: =B6 * Inputs!$B$13 -> 76285000 | F6: =B6 * Inputs!$B$14 -> 34675000 | G6: =Inputs!$B$15 -> 80000000 | H6: =C6 * Inputs!$B$8 -> 1.4448149e+09 | I6: =H6 * Inputs!$B$17 -> 28896298 | J6: =D6 + E6 + F6 + G6 + I6 -> 3.724263e+08 | K6: =J6 / C6 -> 1159.9537
A7: =Production!A7 -> 6 | B7: =Production!B7 -> 1387000 | C7: =Production!E7 -> 321069.98 | D7: =B7 * Inputs!$B$12 -> 152570000 | E7: =B7 * Inputs!$B$13 -> 76285000 | F7: =B7 * Inputs!$B$14 -> 34675000 | G7: =Inputs!$B$15 -> 80000000 | H7: =C7 * Inputs!$B$8 -> 1.4448149e+09 | I7: =H7 * Inputs!$B$17 -> 28896298 | J7: =D7 + E7 + F7 + G7 + I7 -> 3.724263e+08 | K7: =J7 / C7 -> 1159.9537
A8: =Production!A8 -> 7 | B8: =Production!B8 -> 1387000 | C8: =Production!E8 -> 321069.98 | D8: =B8 * Inputs!$B$12 -> 152570000 | E8: =B8 * Inputs!$B$13 -> 76285000 | F8: =B8 * Inputs!$B$14 -> 34675000 | G8: =Inputs!$B$15 -> 80000000 | H8: =C8 * Inputs!$B$8 -> 1.4448149e+09 | I8: =H8 * Inputs!$B$17 -> 28896298 | J8: =D8 + E8 + F8 + G8 + I8 -> 3.724263e+08 | K8: =J8 / C8 -> 1159.9537
A9: =Production!A9 -> 8 | B9: =Production!B9 -> 1387000 | C9: =Production!E9 -> 321069.98 | D9: =B9 * Inputs!$B$12 -> 152570000 | E9: =B9 * Inputs!$B$13 -> 76285000 | F9: =B9 * Inputs!$B$14 -> 34675000 | G9: =Inputs!$B$15 -> 80000000 | H9: =C9 * Inputs!$B$8 -> 1.4448149e+09 | I9: =H9 * Inputs!$B$17 -> 28896298 | J9: =D9 + E9 + F9 + G9 + I9 -> 3.724263e+08 | K9: =J9 / C9 -> 1159.9537
A10: =Production!A10 -> 9 | B10: =Production!B10 -> 1387000 | C10: =Production!E10 -> 321069.98 | D10: =B10 * Inputs!$B$12 -> 152570000 | E10: =B10 * Inputs!$B$13 -> 76285000 | F10: =B10 * Inputs!$B$14 -> 34675000 | G10: =Inputs!$B$15 -> 80000000 | H10: =C10 * Inputs!$B$8 -> 1.4448149e+09 | I10: =H10 * Inputs!$B$17 -> 28896298 | J10: =D10 + E10 + F10 + G10 + I10 -> 3.724263e+08 | K10: =J10 / C10 -> 1159.9537
A11: =Production!A11 -> 10 | B11: =Production!B11 -> 1387000 | C11: =Production!E11 -> 321069.98 | D11: =B11 * Inputs!$B$12 -> 152570000 | E11: =B11 * Inputs!$B$13 -> 76285000 | F11: =B11 * Inputs!$B$14 -> 34675000 | G11: =Inputs!$B$15 -> 80000000 | H11: =C11 * Inputs!$B$8 -> 1.4448149e+09 | I11: =H11 * Inputs!$B$17 -> 28896298 | J11: =D11 + E11 + F11 + G11 + I11 -> 3.724263e+08 | K11: =J11 / C11 -> 1159.9537
A13: Total Cost (CAD) | B13: =SUM(J2:J11) -> 3.724263e+09
A14: Total ounces | B14: =SUM(C2:C11) -> 3210699.8
A15: LOM AISC (CAD/oz) | B15: =B13 / B14 -> 1159.9537
A20: LOM total | B20: =SUM(B2:B11) -> 13870000 | C20: =SUM(C2:C11) -> 3210699.8 | D20: =SUM(D2:D11) -> 1525700000 | E20: =SUM(E2:E11) -> 762850000 | F20: =SUM(F2:F11) -> 346750000 | G20: =SUM(G2:G11) -> 800000000 | H20: =SUM(H2:H11) -> 1.4448149e+10 | I20: =SUM(I2:I11) -> 2.8896298e+08 | J20: =SUM(J2:J11) -> 3.724263e+09

Sheet CashFlow_NPV
A1: Year | B1: Revenue | C1: Total site cost (CAD) | D1: Closure cost (CAD) | E1: Cash flow (CAD) | F1: Discount factor | G1: Discounted CF (CAD)
A2: =Costs_AISC!A2 -> 1 | B2: =Costs_AISC!H2 -> 1.4448149e+09 | C2: =Costs_AISC!J2 -> 3.724263e+08 | D2: 0 | E2: =B2 - C2 - D2 -> 1.0723886e+09 | F2: =1 / (1 + Inputs!$B$18)^A2 -> 0.95238095 | G2: =E2 * F2 -> 1.0213225e+09
A3: =Costs_AISC!A3 -> 2 | B3: =Costs_AISC!H3 -> 1.4448149e+09 | C3: =Costs_AISC!J3 -> 3.724263e+08 | D3: 0 | E3: =B3 - C3 - D3 -> 1.0723886e+09 | F3: =1 / (1 + Inputs!$B$18)^A3 -> 0.90702948 | G3: =E3 * F3 -> 9.7268807e+08
A4: =Costs_AISC!A4 -> 3 | B4: =Costs_AISC!H4 -> 1.4448149e+09 | C4: =Costs_AISC!J4 -> 3.724263e+08 | D4: 0 | E4: =B4 - C4 - D4 -> 1.0723886e+09 | F4: =1 / (1 + Inputs!$B$18)^A4 -> 0.8638376 | G4: =E4 * F4 -> 9.2636959e+08
A5: =Costs_AISC!A5 -> 4 | B5: =Costs_AISC!H5 -> 1.4448149e+09 | C5: =Costs_AISC!J5 -> 3.724263e+08 | D5: 0 | E5: =B5 - C5 - D5 -> 1.0723886e+09 | F5: =1 / (1 + Inputs!$B$18)^A5 -> 0.82270247 | G5: =E5 * F5 -> 8.8225675e+08
A6: =Costs_AISC!A6 -> 5 | B6: =Costs_AISC!H6 -> 1.4448149e+09 | C6: =Costs_AISC!J6 -> 3.724263e+08 | D6: 0 | E6: =B6 - C6 - D6 -> 1.0723886e+09 | F6: =1 / (1 + Inputs!$B$18)^A6 -> 0.78352617 | G6: =E6 * F6 -> 8.4024452e+08
A7: =Costs_AISC!A7 -> 6 | B7: =Costs_AISC!H7 -> 1.4448149e+09 | C7: =Costs_AISC!J7 -> 3.724263e+08 | D7: 0 | E7: =B7 - C7 - D7 -> 1.0723886e+09 | F7: =1 / (1 + Inputs!$B$18)^A7 -> 0.7462154 | G7: =E7 * F7 -> 8.0023288e+08
A8: =Costs_AISC!A8 -> 7 | B8: =Costs_AISC!H8 -> 1.4448149e+09 | C8: =Costs_AISC!J8 -> 3.724263e+08 | D8: 0 | E8: =B8 - C8 - D8 -> 1.0723886e+09 | F8: =1 / (1 + Inputs!$B$18)^A8 -> 0.71068133 | G8: =E8 * F8 -> 7.6212655e+08
A9: =Costs_AISC!A9 -> 8 | B9: =Costs_AISC!H9 -> 1.4448149e+09 | C9: =Costs_AISC!J9 -> 3.724263e+08 | D9: 0 | E9: =B9 - C9 - D9 -> 1.0723886e+09 | F9: =1 / (1 + Inputs!$B$18)^A9 -> 0.67683936 | G9: =E9 * F9 -> 7.2583481e+08
A10: =Costs_AISC!A10 -> 9 | B10: =Costs_AISC!H10 -> 1.4448149e+09 | C10: =Costs_AISC!J10 -> 3.724263e+08 | D10: 0 | E10: =B10 - C10 - D10 -> 1.0723886e+09 | F10: =1 / (1 + Inputs!$B$18)^A10 -> 0.64460892 | G10: =E10 * F10 -> 6.9127125e+08
A11: =Costs_AISC!A11 -> 10 | B11: =Costs_AISC!H11 -> 1.4448149e+09 | C11: =Costs_AISC!J11 -> 3.724263e+08 | D11: =Inputs!$B$15 -> 80000000 | E11: =B11 - C11 - D11 -> 9.9238859e+08 | F11: =1 / (1 + Inputs!$B$18)^A11 -> 0.61391325 | G11: =E11 * F11 -> 6.0924051e+08
A13: NPV (CAD) | B13: =SUM(G2:G11) -> 8.2315874e+09

Sheet Sensitivites
A1: Variable | B1: Multiplier | C1: NPV
A2: Grade | B2: 0.8 | C2: 6.0449178e+09
A3: Grade | B3: 0.9 | C3: 7.1382526e+09
A4: Grade | B4: 1 | C4: 8.2315874e+09
A5: Grade | B5: 1.1 | C5: 9.3249222e+09
A6: Grade | B6: 1.2 | C6: 1.0418257e+10

Sheet Charts
A1: Mining | B1: =Costs_AISC!D20/Costs_AISC!C20 -> 475.19236
A2: Processing | B2: =Costs_AISC!E20/Costs_AISC!C20 -> 237.59618
A3: G&A | B3: =Costs_AISC!F20/Costs_AISC!C20 -> 107.99826
A4: Sustaining capital | B4: =Costs_AISC!G20/Costs_AISC!C20 -> 249.16687
A5: Royalty | B5: =Costs_AISC!I20/Costs_AISC!C20 -> 90
A6: AISC | B6: =Costs_AISC!B15 -> 1159.9537
A19: Gold Price | B19: NPV
A20: 3500 | B20: 5.8019545e+09
A21: 4000 | B21: 7.016771e+09
A22: 4500 | B22: 8.2315874e+09
A23: 5000 | B23: 9.4464039e+09
A24: 5500 | B24: 1.066122e+10
A56: Variable | B56: Low Case NPV | C56: Base Case NPV | D56: High Case NPV | E56: Impact
A57: Gold price | B57: 5.8019545e+09 | C57: 8.2315874e+09 | D57: 1.066122e+10 | E57: =D57-B57 -> 4.8592658e+09
A58: Grade | B58: 6.0449178e+09 | C58: 8.2315874e+09 | D58: 1.0418257e+10 | E58: =D58-B58 -> 4.3733392e+09
A59: Sustaining capital | B59: =Costs_AISC!G2*0.8 -> 64000000 | C59: =Costs_AISC!G2 -> 80000000 | D59: =Costs_AISC!G2*1.2 -> 96000000 | E59: =D59-B59 -> 32000000
A60: Mining cost | B60: =Costs_AISC!D2*0.9 -> 137313000 | C60: =Costs_AISC!D2 -> 152570000 | D60: =Costs_AISC!D2*1.1 -> 167827000 | E60: =D60-B60 -> 30514000
A61: Processing cost | B61: =Costs_AISC!E2*0.9 -> 68656500 | C61: =Costs_AISC!E2 -> 76285000 | D61: =Costs_AISC!E2*1.1 -> 83913500 | E61: =D61-B61 -> 15257000
A63: Variable | B63: Low ΔNPV | C63: High ΔNPV
A64: Gold price | B64: =B57-C57 -> -2.4296329e+09 | C64: =D57-C57 -> 2.4296329e+09
A65: Grade | B65: =B58-C58 -> -2.1866696e+09 | C65: =D58-C58 -> 2.1866696e+09
A66: Sustaining capital | B66: =B59-C59 -> -16000000 | C66: =D59-C59 -> 16000000
A67: Mining cost | B67: =B60-C60 -> -15257000 | C67: =D60-C60 -> 15257000
A68: Processing cost | B68: =B61-C61 -> -7628500 | C68: =D61-C61 -> 7628500
